1、代码内容

````java
public class Hello {
    public static void main(String[] args) {
        int max = 10;
        for (int i=0;i<max;i++){
            if(i%2 != 0){
                System.out.println("=====" + i);
            }
        }
    }
}
````
2、编译文件，**分析结果已加注释**

````shell
conglongli@localhost homework % javac -g Hello.java
conglongli@localhost homework % javap -c -verbose Hello.class
# 文件描述信息，例如：描述修改时间、大小等内容、描述MD5加密信息、编译文件来源
Classfile /Users/conglongli/Documents/workspace/java-training-camp/01-JVM进阶/homework/Hello.class
  Last modified 2022年5月2日; size 1045 bytes            
  MD5 checksum 745b60e10f7786d07712b14fca249f9d				 
  Compiled from "Hello.java"			
# 类描述信息，例如：类名、主副版本号、修饰符、是否有父类、当前类在常量池的位置、父类在常量池的位置、接口数量、属性数量、方法数量、参数数量
public class Hello																		
  minor version: 0
  major version: 55
  flags: (0x0021) ACC_PUBLIC, ACC_SUPER
  this_class: #5                          // Hello
  super_class: #6                         // java/lang/Object
  interfaces: 0, fields: 0, methods: 2, attributes: 3
# 常量池
Constant pool:
   #1 = Methodref          #6.#24         // java/lang/Object."<init>":()V   
   #2 = Fieldref           #25.#26        // java/lang/System.out:Ljava/io/PrintStream;
   #3 = InvokeDynamic      #0:#30         // #0:makeConcatWithConstants:(I)Ljava/lang/String;
   #4 = Methodref          #31.#32        // java/io/PrintStream.println:(Ljava/lang/String;)V
   #5 = Class              #33            // Hello
   #6 = Class              #34            // java/lang/Object
   #7 = Utf8               <init>
   #8 = Utf8               ()V
   #9 = Utf8               Code
  #10 = Utf8               LineNumberTable
  #11 = Utf8               LocalVariableTable
  #12 = Utf8               this
  #13 = Utf8               LHello;
  #14 = Utf8               main
  #15 = Utf8               ([Ljava/lang/String;)V
  #16 = Utf8               i
  #17 = Utf8               I
  #18 = Utf8               args
  #19 = Utf8               [Ljava/lang/String;
  #20 = Utf8               max
  #21 = Utf8               StackMapTable
  #22 = Utf8               SourceFile
  #23 = Utf8               Hello.java
  #24 = NameAndType        #7:#8          // "<init>":()V
  #25 = Class              #35            // java/lang/System
  #26 = NameAndType        #36:#37        // out:Ljava/io/PrintStream;
  #27 = Utf8               BootstrapMethods
  #28 = MethodHandle       6:#38          // REF_invokeStatic java/lang/invoke/StringConcatFactory.makeConcatWithConstants:(Ljava/lang/invoke/MethodHandles$Lookup;Ljava/lang/String;Ljava/lang/invoke/MethodType;Ljava/lang/String;[Ljava/lang/Object;)Ljava/lang/invoke/CallSite;
  #29 = String             #39            // =====\u0001
  #30 = NameAndType        #40:#41        // makeConcatWithConstants:(I)Ljava/lang/String;
  #31 = Class              #42            // java/io/PrintStream
  #32 = NameAndType        #43:#44        // println:(Ljava/lang/String;)V
  #33 = Utf8               Hello
  #34 = Utf8               java/lang/Object
  #35 = Utf8               java/lang/System
  #36 = Utf8               out
  #37 = Utf8               Ljava/io/PrintStream;
  #38 = Methodref          #45.#46        // java/lang/invoke/StringConcatFactory.makeConcatWithConstants:(Ljava/lang/invoke/MethodHandles$Lookup;Ljava/lang/String;Ljava/lang/invoke/MethodType;Ljava/lang/String;[Ljava/lang/Object;)Ljava/lang/invoke/CallSite;
  #39 = Utf8               =====\u0001
  #40 = Utf8               makeConcatWithConstants
  #41 = Utf8               (I)Ljava/lang/String;
  #42 = Utf8               java/io/PrintStream
  #43 = Utf8               println
  #44 = Utf8               (Ljava/lang/String;)V
  #45 = Class              #47            // java/lang/invoke/StringConcatFactory
  #46 = NameAndType        #40:#51        // makeConcatWithConstants:(Ljava/lang/invoke/MethodHandles$Lookup;Ljava/lang/String;Ljava/lang/invoke/MethodType;Ljava/lang/String;[Ljava/lang/Object;)Ljava/lang/invoke/CallSite;
  #47 = Utf8               java/lang/invoke/StringConcatFactory
  #48 = Class              #53            // java/lang/invoke/MethodHandles$Lookup
  #49 = Utf8               Lookup
  #50 = Utf8               InnerClasses
  #51 = Utf8               (Ljava/lang/invoke/MethodHandles$Lookup;Ljava/lang/String;Ljava/lang/invoke/MethodType;Ljava/lang/String;[Ljava/lang/Object;)Ljava/lang/invoke/CallSite;
  #52 = Class              #54            // java/lang/invoke/MethodHandles
  #53 = Utf8               java/lang/invoke/MethodHandles$Lookup
  #54 = Utf8               java/lang/invoke/MethodHandles
{
  public Hello();                               # 构造函数
    descriptor: ()V                              # 返回值为void
    flags: (0x0001) ACC_PUBLIC                              # 修饰符为public
    Code:
      stack=1, locals=1, args_size=1                              # 栈的深度为1，本地变量个数为1，参数个数为1
         0: aload_0                              # 将本地变量表Slot为0的变量压栈
         1: invokespecial #1                  // Method java/lang/Object."<init>":()V   # 方法调用，即调用构造函数
         4: return                              # 返回
      LineNumberTable:                              # 栈的深度
        line 1: 0
      LocalVariableTable:	                              # 本地变量表
        Start  Length  Slot  Name   Signature
            0       5     0  this   LHello;

  public static void main(java.lang.String[]);                              # main方法
    descriptor: ([Ljava/lang/String;)V                              # 返回值为 void
    flags: (0x0009) ACC_PUBLIC, ACC_STATIC                              # 修饰符为public static
    Code:
      stack=2, locals=3, args_size=1	                              # 站的深度为2，本地变量3个，参数1个
         0: bipush        10	                              # 将10压栈
         2: istore_1                              # 将栈顶数据放入本地变量表Slot=1的位置
         3: iconst_0                              # 将0压入栈
         4: istore_2                              # 将栈顶内容放入本地变量表Slot=2的位置
         5: iload_2                              # load Slot=2的内容
         6: iload_1                              # load Slot=1的内容
         7: if_icmpge     34                    # 对比，如果对比不成功，继续向下执行，对比成功，则执行偏移量为34的命令
        10: iload_2                              # load Slot=2的内容
        11: iconst_2                              # 将2压入栈
        12: irem                              # 弹出栈顶两个数，进行取模操作
        13: ifeq          28                     # 如果栈顶为0（即上一步计算结果为0），执行28，不为0，继续向下执行
        16: getstatic     #2        // Field java/lang/System.out:Ljava/io/PrintStream; 	# 输出Slot=2的内容
        19: iload_2                              # load Slot=2的内容
        20: invokedynamic #3,  0    // InvokeDynamic #0:makeConcatWithConstants:(I)Ljava/lang/String;# 方法调用
        25: invokevirtual #4         // Method java/io/PrintStream.println:(Ljava/lang/String;)V  # 方法调用
        28: iinc          2, 1									# 自增
        31: goto          5									    # 跳转执行5
        34: return															# 返回
      LineNumberTable:                              # 操作数栈
        line 3: 0
        line 4: 3
        line 5: 10
        line 6: 16
        line 4: 28
        line 9: 34
      LocalVariableTable:                              # 本地变量表
        Start  Length  Slot  Name   Signature
            5      29     2     i   I
            0      35     0  args   [Ljava/lang/String;
            3      32     1   max   I
      StackMapTable: number_of_entries = 3
        frame_type = 253 /* append */
          offset_delta = 5
          locals = [ int, int ]
        frame_type = 22 /* same */
        frame_type = 250 /* chop */
          offset_delta = 5
}
SourceFile: "Hello.java"
InnerClasses:
  public static final #49= #48 of #52;    // Lookup=class java/lang/invoke/MethodHandles$Lookup of class java/lang/invoke/MethodHandles
BootstrapMethods:
  0: #28 REF_invokeStatic java/lang/invoke/StringConcatFactory.makeConcatWithConstants:(Ljava/lang/invoke/MethodHandles$Lookup;Ljava/lang/String;Ljava/lang/invoke/MethodType;Ljava/lang/String;[Ljava/lang/Object;)Ljava/lang/invoke/CallSite;
    Method arguments:
      #29 =====\u0001
````

